slip_plate/__init__.py
slip_plate/__main__.py
slip_plate/checksum.py
slip_plate/cli.py
slip_plate/crypto.py
slip_plate/plate.py
slip_plate/shamir.py
slip_plate/slip_plate.py
slip_plate/utils.py
slip_plate-0.1.3.dist-info/licenses/LICENSE
slip_plate-0.1.3.dist-info/METADATA
slip_plate-0.1.3.dist-info/WHEEL
slip_plate-0.1.3.dist-info/entry_points.txt
slip_plate-0.1.3.dist-info/top_level.txt
slip_plate-0.1.3.dist-info/RECORD
