Metadata-Version: 2.4
Name: slip-plate
Version: 0.1.3
Summary: A seed plate scanner and parser tool
Author-email: avra911 <java-hug-circulate@duck.com>
License: MIT
Classifier: Programming Language :: Python :: 3
Classifier: License :: OSI Approved :: MIT License
Classifier: Operating System :: OS Independent
Requires-Python: >=3.8
License-File: LICENSE
Requires-Dist: cryptography==41.0.4
Requires-Dist: pyshamir==1.0.4
Dynamic: license-file
